{"ast":null,"code":"import flatpickr from \"flatpickr\";\nimport \"flatpickr/dist/flatpickr.min.css\";\nimport rangePlugin from \"flatpickr/dist/plugins/rangePlugin\";\nimport { French } from \"flatpickr/dist/l10n/fr.js\"; // flatpickr(\".datepicker\", {})\n\nflatpickr(\"#range_start\", {\n  mode: \"range\",\n  locale: French\n});","map":{"version":3,"sources":["/Users/xgastaud/code/xgastaud/endurace2/app/javascript/plugins/flatpickr.js"],"names":["flatpickr","rangePlugin","French","mode","locale"],"mappings":"AAAA,OAAOA,SAAP,MAAsB,WAAtB;AACA,OAAO,kCAAP;AACA,OAAOC,WAAP,MAAwB,oCAAxB;AACA,SAASC,MAAT,QAAuB,2BAAvB,C,CAEA;;AAEAF,SAAS,CAAC,cAAD,EAAiB;AACxBG,EAAAA,IAAI,EAAE,OADkB;AAExBC,EAAAA,MAAM,EAAEF;AAFgB,CAAjB,CAAT","sourcesContent":["import flatpickr from \"flatpickr\"\nimport \"flatpickr/dist/flatpickr.min.css\"\nimport rangePlugin from \"flatpickr/dist/plugins/rangePlugin\"\nimport { French } from \"flatpickr/dist/l10n/fr.js\"\n\n// flatpickr(\".datepicker\", {})\n\nflatpickr(\"#range_start\", {\n  mode: \"range\",\n  locale: French\n})\n"]},"metadata":{},"sourceType":"module"}